AUTHORS
LICENSE
MANIFEST.in
README.rst
setup.py
django_modelish.egg-info/PKG-INFO
django_modelish.egg-info/SOURCES.txt
django_modelish.egg-info/dependency_links.txt
django_modelish.egg-info/entry_points.txt
django_modelish.egg-info/requires.txt
django_modelish.egg-info/top_level.txt
modelish/__init__.py
modelish/args.py
modelish/cli.py
modelish/generate.py
modelish/grammarish.yml