Metadata-Version: 1.0
Name: django-modelish
Version: 0.1
Summary: A simple markup and processor to make initial models.py less tedious
Home-page: http://github.com/ptone/django-modelish
Author: Preston Holmes
Author-email: preston@ptone.com
License: BSD
Platform: UNKNOWN
Classifier: Development Status :: 3 - Alpha
Classifier: Environment :: Web Environment
Classifier: Framework :: Django
Classifier: Intended Audience :: Developers
Classifier: License :: OSI Approved :: BSD License
Classifier: Operating System :: OS Independent
Classifier: Programming Language :: Python
Classifier: Programming Language :: Python :: 2.6
Classifier: Programming Language :: Python :: 2.7
Classifier: Topic :: Utilities
